{"nodes": [{"id": "d_engineering_ode_simulator_analysis_lqr_py", "label": "lqr.py", "file_type": "code", "source_file": "D:\\engineering-ode-simulator\\analysis\\lqr.py", "source_location": "L1"}, {"id": "d_engineering_ode_simulator_analysis_lqr_as_2d_matrix", "label": "_as_2d_matrix()", "file_type": "code", "source_file": "D:\\engineering-ode-simulator\\analysis\\lqr.py", "source_location": "L7", "_callable": true}, {"id": "d_engineering_ode_simulator_analysis_lqr_validate_symmetric", "label": "_validate_symmetric()", "file_type": "code", "source_file": "D:\\engineering-ode-simulator\\analysis\\lqr.py", "source_location": "L20", "_callable": true}, {"id": "d_engineering_ode_simulator_analysis_lqr_validate_positive_semidefinite", "label": "_validate_positive_semidefinite()", "file_type": "code", "source_file": "D:\\engineering-ode-simulator\\analysis\\lqr.py", "source_location": "L26", "_callable": true}, {"id": "d_engineering_ode_simulator_analysis_lqr_validate_lqr_matrices", "label": "validate_lqr_matrices()", "file_type": "code", "source_file": "D:\\engineering-ode-simulator\\analysis\\lqr.py", "source_location": "L34", "_callable": true}, {"id": "d_engineering_ode_simulator_analysis_lqr_lqr", "label": "lqr()", "file_type": "code", "source_file": "D:\\engineering-ode-simulator\\analysis\\lqr.py", "source_location": "L68", "_callable": true}, {"id": "d_engineering_ode_simulator_analysis_lqr_rationale_1", "label": "Continuous-time Linear Quadratic Regulator utilities.", "file_type": "rationale", "source_file": "D:\\engineering-ode-simulator\\analysis\\lqr.py", "source_location": "L1"}, {"id": "d_engineering_ode_simulator_analysis_lqr_rationale_8", "label": "Return a validated two-dimensional float matrix.", "file_type": "rationale", "source_file": "D:\\engineering-ode-simulator\\analysis\\lqr.py", "source_location": "L8"}, {"id": "d_engineering_ode_simulator_analysis_lqr_rationale_21", "label": "Validate that a matrix is symmetric within numerical tolerance.", "file_type": "rationale", "source_file": "D:\\engineering-ode-simulator\\analysis\\lqr.py", "source_location": "L21"}, {"id": "d_engineering_ode_simulator_analysis_lqr_rationale_27", "label": "Validate that a symmetric matrix is positive semidefinite.", "file_type": "rationale", "source_file": "D:\\engineering-ode-simulator\\analysis\\lqr.py", "source_location": "L27"}, {"id": "d_engineering_ode_simulator_analysis_lqr_rationale_35", "label": "Validate continuous-time LQR matrix dimensions and properties.", "file_type": "rationale", "source_file": "D:\\engineering-ode-simulator\\analysis\\lqr.py", "source_location": "L35"}, {"id": "d_engineering_ode_simulator_analysis_lqr_rationale_69", "label": "Compute a continuous-time Linear Quadratic Regulator gain.      The control law", "file_type": "rationale", "source_file": "D:\\engineering-ode-simulator\\analysis\\lqr.py", "source_location": "L69"}], "edges": [{"source": "d_engineering_ode_simulator_analysis_lqr_py", "target": "numpy", "relation": "imports", "context": "import", "confidence": "EXTRACTED", "source_file": "D:\\engineering-ode-simulator\\analysis\\lqr.py", "source_location": "L3", "weight": 1.0}, {"source": "d_engineering_ode_simulator_analysis_lqr_py", "target": "scipy_linalg", "relation": "imports_from", "context": "import", "confidence": "EXTRACTED", "source_file": "D:\\engineering-ode-simulator\\analysis\\lqr.py", "source_location": "L4", "weight": 1.0}, {"source": "d_engineering_ode_simulator_analysis_lqr_py", "target": "d_engineering_ode_simulator_analysis_lqr_as_2d_matrix", "relation": "contains", "confidence": "EXTRACTED", "source_file": "D:\\engineering-ode-simulator\\analysis\\lqr.py", "source_location": "L7", "weight": 1.0}, {"source": "d_engineering_ode_simulator_analysis_lqr_py", "target": "d_engineering_ode_simulator_analysis_lqr_validate_symmetric", "relation": "contains", "confidence": "EXTRACTED", "source_file": "D:\\engineering-ode-simulator\\analysis\\lqr.py", "source_location": "L20", "weight": 1.0}, {"source": "d_engineering_ode_simulator_analysis_lqr_py", "target": "d_engineering_ode_simulator_analysis_lqr_validate_positive_semidefinite", "relation": "contains", "confidence": "EXTRACTED", "source_file": "D:\\engineering-ode-simulator\\analysis\\lqr.py", "source_location": "L26", "weight": 1.0}, {"source": "d_engineering_ode_simulator_analysis_lqr_py", "target": "d_engineering_ode_simulator_analysis_lqr_validate_lqr_matrices", "relation": "contains", "confidence": "EXTRACTED", "source_file": "D:\\engineering-ode-simulator\\analysis\\lqr.py", "source_location": "L34", "weight": 1.0}, {"source": "d_engineering_ode_simulator_analysis_lqr_py", "target": "d_engineering_ode_simulator_analysis_lqr_lqr", "relation": "contains", "confidence": "EXTRACTED", "source_file": "D:\\engineering-ode-simulator\\analysis\\lqr.py", "source_location": "L68", "weight": 1.0}, {"source": "d_engineering_ode_simulator_analysis_lqr_validate_lqr_matrices", "target": "d_engineering_ode_simulator_analysis_lqr_as_2d_matrix", "relation": "calls", "context": "call", "confidence": "EXTRACTED", "source_file": "D:\\engineering-ode-simulator\\analysis\\lqr.py", "source_location": "L36", "weight": 1.0}, {"source": "d_engineering_ode_simulator_analysis_lqr_validate_lqr_matrices", "target": "d_engineering_ode_simulator_analysis_lqr_validate_symmetric", "relation": "calls", "context": "call", "confidence": "EXTRACTED", "source_file": "D:\\engineering-ode-simulator\\analysis\\lqr.py", "source_location": "L56", "weight": 1.0}, {"source": "d_engineering_ode_simulator_analysis_lqr_validate_lqr_matrices", "target": "d_engineering_ode_simulator_analysis_lqr_validate_positive_semidefinite", "relation": "calls", "context": "call", "confidence": "EXTRACTED", "source_file": "D:\\engineering-ode-simulator\\analysis\\lqr.py", "source_location": "L58", "weight": 1.0}, {"source": "d_engineering_ode_simulator_analysis_lqr_lqr", "target": "d_engineering_ode_simulator_analysis_lqr_validate_lqr_matrices", "relation": "calls", "context": "call", "confidence": "EXTRACTED", "source_file": "D:\\engineering-ode-simulator\\analysis\\lqr.py", "source_location": "L82", "weight": 1.0}, {"source": "d_engineering_ode_simulator_analysis_lqr_rationale_1", "target": "d_engineering_ode_simulator_analysis_lqr_py", "relation": "rationale_for", "confidence": "EXTRACTED", "source_file": "D:\\engineering-ode-simulator\\analysis\\lqr.py", "source_location": "L1", "weight": 1.0}, {"source": "d_engineering_ode_simulator_analysis_lqr_rationale_8", "target": "d_engineering_ode_simulator_analysis_lqr_as_2d_matrix", "relation": "rationale_for", "confidence": "EXTRACTED", "source_file": "D:\\engineering-ode-simulator\\analysis\\lqr.py", "source_location": "L8", "weight": 1.0}, {"source": "d_engineering_ode_simulator_analysis_lqr_rationale_21", "target": "d_engineering_ode_simulator_analysis_lqr_validate_symmetric", "relation": "rationale_for", "confidence": "EXTRACTED", "source_file": "D:\\engineering-ode-simulator\\analysis\\lqr.py", "source_location": "L21", "weight": 1.0}, {"source": "d_engineering_ode_simulator_analysis_lqr_rationale_27", "target": "d_engineering_ode_simulator_analysis_lqr_validate_positive_semidefinite", "relation": "rationale_for", "confidence": "EXTRACTED", "source_file": "D:\\engineering-ode-simulator\\analysis\\lqr.py", "source_location": "L27", "weight": 1.0}, {"source": "d_engineering_ode_simulator_analysis_lqr_rationale_35", "target": "d_engineering_ode_simulator_analysis_lqr_validate_lqr_matrices", "relation": "rationale_for", "confidence": "EXTRACTED", "source_file": "D:\\engineering-ode-simulator\\analysis\\lqr.py", "source_location": "L35", "weight": 1.0}, {"source": "d_engineering_ode_simulator_analysis_lqr_rationale_69", "target": "d_engineering_ode_simulator_analysis_lqr_lqr", "relation": "rationale_for", "confidence": "EXTRACTED", "source_file": "D:\\engineering-ode-simulator\\analysis\\lqr.py", "source_location": "L69", "weight": 1.0}], "raw_calls": [{"caller_nid": "d_engineering_ode_simulator_analysis_lqr_as_2d_matrix", "callee": "asarray", "is_member_call": true, "source_file": "D:\\engineering-ode-simulator\\analysis\\lqr.py", "source_location": "L9", "receiver": "np"}, {"caller_nid": "d_engineering_ode_simulator_analysis_lqr_as_2d_matrix", "callee": "float", "is_member_call": false, "indirect": true, "context": "argument", "source_file": "D:\\engineering-ode-simulator\\analysis\\lqr.py", "source_location": "L9"}, {"caller_nid": "d_engineering_ode_simulator_analysis_lqr_as_2d_matrix", "callee": "ValueError", "is_member_call": false, "source_file": "D:\\engineering-ode-simulator\\analysis\\lqr.py", "source_location": "L12", "receiver": null}, {"caller_nid": "d_engineering_ode_simulator_analysis_lqr_as_2d_matrix", "callee": "isfinite", "is_member_call": true, "source_file": "D:\\engineering-ode-simulator\\analysis\\lqr.py", "source_location": "L14", "receiver": "np"}, {"caller_nid": "d_engineering_ode_simulator_analysis_lqr_as_2d_matrix", "callee": "ValueError", "is_member_call": false, "source_file": "D:\\engineering-ode-simulator\\analysis\\lqr.py", "source_location": "L15", "receiver": null}, {"caller_nid": "d_engineering_ode_simulator_analysis_lqr_validate_symmetric", "callee": "allclose", "is_member_call": true, "source_file": "D:\\engineering-ode-simulator\\analysis\\lqr.py", "source_location": "L22", "receiver": "np"}, {"caller_nid": "d_engineering_ode_simulator_analysis_lqr_validate_symmetric", "callee": "ValueError", "is_member_call": false, "source_file": "D:\\engineering-ode-simulator\\analysis\\lqr.py", "source_location": "L23", "receiver": null}, {"caller_nid": "d_engineering_ode_simulator_analysis_lqr_validate_positive_semidefinite", "callee": "eigvalsh", "is_member_call": true, "source_file": "D:\\engineering-ode-simulator\\analysis\\lqr.py", "source_location": "L28", "receiver": null}, {"caller_nid": "d_engineering_ode_simulator_analysis_lqr_validate_positive_semidefinite", "callee": "ValueError", "is_member_call": false, "source_file": "D:\\engineering-ode-simulator\\analysis\\lqr.py", "source_location": "L31", "receiver": null}, {"caller_nid": "d_engineering_ode_simulator_analysis_lqr_validate_lqr_matrices", "callee": "ValueError", "is_member_call": false, "source_file": "D:\\engineering-ode-simulator\\analysis\\lqr.py", "source_location": "L45", "receiver": null}, {"caller_nid": "d_engineering_ode_simulator_analysis_lqr_validate_lqr_matrices", "callee": "ValueError", "is_member_call": false, "source_file": "D:\\engineering-ode-simulator\\analysis\\lqr.py", "source_location": "L48", "receiver": null}, {"caller_nid": "d_engineering_ode_simulator_analysis_lqr_validate_lqr_matrices", "callee": "ValueError", "is_member_call": false, "source_file": "D:\\engineering-ode-simulator\\analysis\\lqr.py", "source_location": "L51", "receiver": null}, {"caller_nid": "d_engineering_ode_simulator_analysis_lqr_validate_lqr_matrices", "callee": "ValueError", "is_member_call": false, "source_file": "D:\\engineering-ode-simulator\\analysis\\lqr.py", "source_location": "L54", "receiver": null}, {"caller_nid": "d_engineering_ode_simulator_analysis_lqr_validate_lqr_matrices", "callee": "cholesky", "is_member_call": true, "source_file": "D:\\engineering-ode-simulator\\analysis\\lqr.py", "source_location": "L61", "receiver": null}, {"caller_nid": "d_engineering_ode_simulator_analysis_lqr_validate_lqr_matrices", "callee": "ValueError", "is_member_call": false, "source_file": "D:\\engineering-ode-simulator\\analysis\\lqr.py", "source_location": "L63", "receiver": null}, {"caller_nid": "d_engineering_ode_simulator_analysis_lqr_lqr", "callee": "solve_continuous_are", "is_member_call": false, "source_file": "D:\\engineering-ode-simulator\\analysis\\lqr.py", "source_location": "L84", "receiver": null}, {"caller_nid": "d_engineering_ode_simulator_analysis_lqr_lqr", "callee": "solve", "is_member_call": true, "source_file": "D:\\engineering-ode-simulator\\analysis\\lqr.py", "source_location": "L85", "receiver": null}, {"caller_nid": "d_engineering_ode_simulator_analysis_lqr_lqr", "callee": "eigvals", "is_member_call": true, "source_file": "D:\\engineering-ode-simulator\\analysis\\lqr.py", "source_location": "L86", "receiver": null}]}